{"cameraMode":{"drawMode":0,"name":"Shaded","section":"Shading Mode"},"sceneLighting":true,"audioPlay":false,"sceneViewState":{"m_AlwaysRefresh":false,"showFog":true,"showSkybox":true,"showFlares":true,"showImageEffects":true,"showParticleSystems":true,"showVisualEffectGraphs":true,"m_FxEnabled":true},"in2DMode":false,"pivot":{"x":0.7332510948181152,"y":1.273007869720459,"z":3.1282901763916017},"rotation":{"x":-0.12585152685642243,"y":0.043731238692998889,"z":-0.0055536613799631599,"w":-0.9910699725151062},"size":13.813672065734864,"orthographic":false}